protectremote/__init__.py
protectremote/file.py
protectremote/job.py
protectremote/main.py
protectremote/middleware.py
protectremote/settings.py
protectremote/version.py
protectremote/templates/Forbidden403Page.html
protectremote-0.0.0.8.dist-info/LICENSE.txt
protectremote-0.0.0.8.dist-info/METADATA
protectremote-0.0.0.8.dist-info/WHEEL
protectremote-0.0.0.8.dist-info/top_level.txt
protectremote-0.0.0.8.dist-info/RECORD
