Metadata-Version: 2.1
Name: protectremote
Version: 0.0.0.8
Summary: Next-gen security solution for remote workers
Author: Protect Remote
Author-email: sinan.bozkus@gmail.com
License: MIT
Keywords: security
License-File: LICENSE.txt
Requires-Dist: python-settings
Requires-Dist: requests
Requires-Dist: flask
Requires-Dist: apscheduler
Requires-Dist: python-dotenv
